datamastery/__init__.py
datamastery/chart.py
datamastery/preprocessing.py
datamastery-0.1.2.dist-info/LICENCE
datamastery-0.1.2.dist-info/METADATA
datamastery-0.1.2.dist-info/WHEEL
datamastery-0.1.2.dist-info/top_level.txt
datamastery-0.1.2.dist-info/RECORD
