Metadata-Version: 2.1
Name: datamastery
Version: 0.1.2
Summary: Contains useful functions for data science
Download-URL: http://pypi.python.org/pypi/datamastery
Author: Baran Kutluay
Author-email: barankutluay19@gmail.com
License: MIT
Classifier: Development Status :: 1 - Planning
Classifier: Programming Language :: Python :: 3
Classifier: Topic :: Software Development :: Libraries :: Python Modules
License-File: LICENCE
Requires-Dist: setuptools (>=65.5.0)
Requires-Dist: matplotlib (>=3.6.3)
Requires-Dist: numpy (>=1.24.1)
Requires-Dist: seaborn (>=0.12.2)
Requires-Dist: pandas (>=1.5.3)
